qpcr/__init__.py
qpcr/Curves/EfficiencyCurve.py
qpcr/Curves/__init__.py
qpcr/Filters/Filters.py
qpcr/Filters/__init__.py
qpcr/Parsers/Parsers.py
qpcr/Parsers/__init__.py
qpcr/Pipes/Pipes.py
qpcr/Pipes/__init__.py
qpcr/Plotters/AssaySubplotResults.py
qpcr/Plotters/EfficiencyLines.py
qpcr/Plotters/FilterSummary.py
qpcr/Plotters/GroupSubplotResults.py
qpcr/Plotters/PairwiseHeatmap.py
qpcr/Plotters/PairwisePlot.py
qpcr/Plotters/PreviewResults.py
qpcr/Plotters/ReplicateBoxPlot.py
qpcr/Plotters/__init__.py
qpcr/Plotters/_base.py
qpcr/Plotters/func_api.py
qpcr/Readers/Readers.py
qpcr/Readers/__init__.py
qpcr/_auxiliary/__init__.py
qpcr/_auxiliary/graphical.py
qpcr/_auxiliary/warnings/__init__.py
qpcr/_auxiliary/warnings/warnings.py
qpcr/defaults/__init__.py
qpcr/defaults/defaults.py
qpcr/main/Analyser.py
qpcr/main/Assay.py
qpcr/main/Calibrator.py
qpcr/main/DataReader.py
qpcr/main/Normaliser.py
qpcr/main/Results.py
qpcr/main/__init__.py
qpcr/main/func_api.py
qpcr/stats/Anova.py
qpcr/stats/Comparisons.py
qpcr/stats/Evaluator.py
qpcr/stats/PairwiseTests.py
qpcr/stats/StatsTest.py
qpcr/stats/__init__.py
qpcr/stats/func_api.py
qpcr-4.1.4.dist-info/licenses/LICENSE
qpcr-4.1.4.dist-info/METADATA
qpcr-4.1.4.dist-info/WHEEL
qpcr-4.1.4.dist-info/top_level.txt
qpcr-4.1.4.dist-info/RECORD
