Metadata-Version: 2.4
Name: qpcr
Version: 4.1.4
Summary: A python package to perform analysis of qPCR data
Home-page: https://github.com/NoahHenrikKleinschmidt/qpcr.git
Author: Noah H. Kleinschmidt
Author-email: noah.kleinschmidt@students.unibe.ch
Classifier: Programming Language :: Python :: 3
Classifier: License :: OSI Approved :: GNU General Public License v3 (GPLv3)
Classifier: Operating System :: OS Independent
Classifier: Topic :: Scientific/Engineering :: Bio-Informatics
Requires-Python: >=3.8
License-File: LICENSE
Requires-Dist: numpy
Requires-Dist: pandas
Requires-Dist: scipy
Requires-Dist: matplotlib
Requires-Dist: seaborn
Requires-Dist: statsmodels
Requires-Dist: plotly
Requires-Dist: statannotations
Dynamic: author
Dynamic: author-email
Dynamic: classifier
Dynamic: description
Dynamic: description-content-type
Dynamic: home-page
Dynamic: license-file
Dynamic: requires-dist
Dynamic: requires-python
Dynamic: summary
